HISTORY.rst
MANIFEST.in
README.rst
setup.py
doc/compatibility.rst
doc/conf.py
doc/general.rst
doc/html40_19991224.rst
doc/http.rst
doc/ims.rst
doc/imsbltiv1p0.rst
doc/imscpv1p2.rst
doc/imsqtiv1p2p1.rst
doc/imsqtiv2p1.rst
doc/index.rst
doc/iso8601.rst
doc/odatav2.rst
doc/odatav2_client.rst
doc/odatav2_consumer.rst
doc/odatav2_core.rst
doc/odatav2_csdl.rst
doc/odatav2_customexample.rst
doc/odatav2_memds.rst
doc/odatav2_memexample.rst
doc/odatav2_metadata.rst
doc/odatav2_provider.rst
doc/odatav2_reference.rst
doc/odatav2_server.rst
doc/odatav2_sqlds.rst
doc/odatav2_sqlexample.rst
doc/pep8.rst
doc/py2.rst
doc/py26.rst
doc/rfc2396.rst
doc/rfc4287.rst
doc/rfc5023.rst
doc/unicode5.rst
doc/vfs.rst
doc/whatsnew.rst
doc/wsgi.rst
doc/xml20081126.parser.rst
doc/xml20081126.rst
doc/xsdatatypes20041028.rst
doc/http/auth.rst
doc/http/client.rst
doc/http/cookie.rst
doc/http/grammar.rst
doc/http/messages.rst
doc/http/params.rst
doc/images/cachefilter.png
doc/images/dataservices.png
doc/images/fsodata.png
doc/images/launch.png
doc/images/navcollection.png
doc/images/temperatures.png
doc/images/weeklyblog.png
doc/qtiv1/common.rst
doc/qtiv1/core.rst
doc/qtiv2/content.rst
doc/qtiv2/core.rst
doc/qtiv2/expressions.rst
doc/qtiv2/interactions.rst
doc/qtiv2/items.rst
doc/qtiv2/metadata.rst
doc/qtiv2/processing.rst
doc/qtiv2/tests.rst
doc/qtiv2/variables.rst
pyslet/__init__.py
pyslet/blockstore.py
pyslet/html40_19991224.py
pyslet/imsbltiv1p0.py
pyslet/imsbltiv1p0_metadata.xml
pyslet/imscc_profilev1p0.py
pyslet/imscc_profilev1p1.py
pyslet/imscpv1p2.py
pyslet/imsmdv1p2p1.py
pyslet/imsqtiv1p2p1.py
pyslet/imsqtiv2p1.py
pyslet/info.py
pyslet/iso8601.py
pyslet/mysqldbds.py
pyslet/pep8.py
pyslet/py2.py
pyslet/py26.py
pyslet/qml420.py
pyslet/rfc2396.py
pyslet/rfc2616.py
pyslet/rfc2617.py
pyslet/rfc4287.py
pyslet/rfc5023.py
pyslet/rtf_1p6.py
pyslet/unicode5.py
pyslet/unicode5_blocks.pck
pyslet/unicode5_blocks3.pck
pyslet/unicode5_catogories.pck
pyslet/unicode5_catogories3.pck
pyslet.egg-info/PKG-INFO
pyslet.egg-info/SOURCES.txt
pyslet.egg-info/dependency_links.txt
pyslet.egg-info/top_level.txt
